phoney/__init__.py
phoney/age.py
phoney/agent.py
phoney/barcode.py
phoney/career.py
phoney/create_profile.py
phoney/data_loader.py
phoney/emailgen.py
phoney/financial.py
phoney/imei.py
phoney/internet.py
phoney/person.py
phoney/phone.py
phoney/resume.py
phoney/username.py
phoney/uuidgen.py
phoney/vin.py
phoney/data/email_domains.json
phoney/data/phone_formats.json
phoney/data/career/companies.de_DE.txt
phoney/data/career/companies.en_GB.txt
phoney/data/career/companies.en_US.txt
phoney/data/career/job_families.json
phoney/data/career/salary_ranges.de_DE.json
phoney/data/career/salary_ranges.en_GB.json
phoney/data/career/salary_ranges.en_US.json
phoney/data/career/skills.json
phoney/data/internet/ipv6_prefixes.GB.txt
phoney/data/internet/tlds.txt
phoney/data/internet/words.txt
phoney/data/name_data/asian/hi_IN/female.txt
phoney/data/name_data/asian/hi_IN/last.txt
phoney/data/name_data/asian/hi_IN/male.txt
phoney/data/name_data/asian/ja_JP/female.txt
phoney/data/name_data/asian/ja_JP/last.txt
phoney/data/name_data/asian/ja_JP/male.txt
phoney/data/name_data/asian/ko_KR/female.txt
phoney/data/name_data/asian/ko_KR/last.txt
phoney/data/name_data/asian/ko_KR/male.txt
phoney/data/name_data/asian/zh_CN/female.txt
phoney/data/name_data/asian/zh_CN/last.txt
phoney/data/name_data/asian/zh_CN/male.txt
phoney/data/name_data/european/da_DK/female.txt
phoney/data/name_data/european/da_DK/last.txt
phoney/data/name_data/european/da_DK/male.txt
phoney/data/name_data/european/de_DE/female.txt
phoney/data/name_data/european/de_DE/last.txt
phoney/data/name_data/european/de_DE/male.txt
phoney/data/name_data/european/en_GB/female.txt
phoney/data/name_data/european/en_GB/last.txt
phoney/data/name_data/european/en_GB/male.txt
phoney/data/name_data/european/en_US/female.txt
phoney/data/name_data/european/en_US/last.txt
phoney/data/name_data/european/en_US/male.txt
phoney/data/name_data/european/es_ES/female.txt
phoney/data/name_data/european/es_ES/last.txt
phoney-0.3.1.dist-info/entry_points.txt
phoney-0.3.1.dist-info/WHEEL
phoney-0.3.1.dist-info/METADATA
phoney-0.3.1.dist-info/RECORD
