Metadata-Version: 2.4
Name: phoney
Version: 0.3.1
Summary: A fake information generator for creating realistic personal data including names, phone numbers, emails, and more.
Keywords: fake data,testing,generator,mock,personal information
Author-email: rarfile <d7276250@email.com>
Maintainer-email: rarfile <d7276250@email.com>
Requires-Python: >=3.10
Classifier: Development Status :: 4 - Beta
Classifier: Intended Audience :: Developers
Classifier: License :: OSI Approved :: MIT License
Classifier: Programming Language :: Python :: 3
Classifier: Programming Language :: Python :: 3.10
Classifier: Programming Language :: Python :: 3.11
Classifier: Programming Language :: Python :: 3.12
Classifier: Programming Language :: Python :: 3.13
Classifier: Operating System :: OS Independent
Classifier: Topic :: Software Development :: Libraries :: Python Modules
Classifier: Topic :: Utilities
Project-URL: Changelog, https://github.com/YTstyo/phoney/releases
Project-URL: Homepage, https://github.com/YTstyo/phoney
Project-URL: Issues, https://github.com/YTstyo/phoney/issues
Project-URL: Repository, https://github.com/YTstyo/phoney
